README.md
setup.py
devpro1.egg-info/PKG-INFO
devpro1.egg-info/SOURCES.txt
devpro1.egg-info/dependency_links.txt
devpro1.egg-info/not-zip-safe
devpro1.egg-info/requires.txt
devpro1.egg-info/top_level.txt
libpythonpro/__init__.py
libpythonpro/github_api.py
libpythonpro/spam/__init__.py
libpythonpro/spam/db.py
libpythonpro/spam/enviador_de_email.py
libpythonpro/spam/modelos.py
libpythonpro/tests/__init__.py
libpythonpro/tests/test_exemplo.py
libpythonpro/tests/test_spam/__init__.py
libpythonpro/tests/test_spam/test_enviador_de_email.py
libpythonpro/tests/test_spam/test_usuario.py